walkmapper/__init__.py
walkmapper/routes.py
walkmapper/utils.py
walkmapper2-0.1.3.dist-info/LICENSE
walkmapper2-0.1.3.dist-info/METADATA
walkmapper2-0.1.3.dist-info/WHEEL
walkmapper2-0.1.3.dist-info/top_level.txt
walkmapper2-0.1.3.dist-info/RECORD
