Metadata-Version: 2.1
Name: walkmapper2
Version: 0.1.3
Summary: A package for plotting and animating .gpx files
Home-page: https://codeberg.org/ktprograms/walkmapper
Author: Keith Toh
Author-email: ktprograms@gmail.com
License: UNKNOWN
Platform: UNKNOWN
Classifier: Programming Language :: Python :: 3
Classifier: License :: OSI Approved :: MIT License
Classifier: Operating System :: OS Independent
Requires-Python: >=3.6
License-File: LICENSE
